step_detection/__init__.py
step_detection/base.py
step_detection/costs/__init__.py
step_detection/costs/cost_mean_dist.py
step_detection/costs/cost_median_dist.py
step_detection/costs/cost_min_max_dist.py
step_detection/detection/__init__.py
step_detection/detection/escalator_rush.py
escalator_nyandams-0.0.2.dist-info/LICENSE
escalator_nyandams-0.0.2.dist-info/METADATA
escalator_nyandams-0.0.2.dist-info/WHEEL
escalator_nyandams-0.0.2.dist-info/top_level.txt
escalator_nyandams-0.0.2.dist-info/RECORD
