Metadata-Version: 2.1
Name: escalator-nyandams
Version: 0.0.2
Summary: A small package to detect stagnation in the values of a signal, sort of horizontal steps
Home-page: https://github.com/Nyandams/step_detection
Author: Damien Lecha
Author-email: lecha.damien@gmail.com
License: UNKNOWN
Platform: UNKNOWN
Classifier: Programming Language :: Python :: 3
Classifier: License :: OSI Approved :: MIT License
Classifier: Operating System :: OS Independent
Requires-Python: >=3.6
